backend/__init__.py
backend/routes/__init__.py
backend/services/__init__.py
core/__init__.py
flet_devtools-0.0.0.dist-info/licenses/LICENSE
frontend/__init__.py
frontend/reflex_ui/__init__.py
frontend/web/__init__.py
modules/__init__.py
modules/inspector/__init__.py
utils/__init__.py
flet_devtools-0.0.0.dist-info/METADATA
flet_devtools-0.0.0.dist-info/WHEEL
flet_devtools-0.0.0.dist-info/top_level.txt
flet_devtools-0.0.0.dist-info/RECORD
