Metadata-Version: 2.4
Name: flet-devtools
Version: 0.0.0
Summary: Web-based DevTools for Flet applications - Similar to Flutter DevTools
Author-email: brunobrown <brunobrown.86@gmail.com>
License-Expression: MIT
Project-URL: Homepage, https://github.com/brunobrown/flet-devtools
Project-URL: Repository, https://github.com/brunobrown/flet-devtools
Project-URL: Issues, https://github.com/brunobrown/flet-devtools/issues
Requires-Python: >=3.9
License-File: LICENSE
Requires-Dist: flet>=0.28.3
Provides-Extra: web
Requires-Dist: fastapi>=0.115.0; extra == "web"
Requires-Dist: uvicorn[standard]>=0.32.0; extra == "web"
Requires-Dist: websockets>=14.0; extra == "web"
Provides-Extra: reflex
Requires-Dist: fastapi>=0.115.0; extra == "reflex"
Requires-Dist: uvicorn[standard]>=0.32.0; extra == "reflex"
Provides-Extra: all
Requires-Dist: fastapi>=0.115.0; extra == "all"
Requires-Dist: uvicorn[standard]>=0.32.0; extra == "all"
Requires-Dist: websockets>=14.0; extra == "all"
Dynamic: license-file
